lambda_decorators.py
lambda_decorators-0.6.0.dist-info/LICENSE
lambda_decorators-0.6.0.dist-info/METADATA
lambda_decorators-0.6.0.dist-info/WHEEL
lambda_decorators-0.6.0.dist-info/top_level.txt
lambda_decorators-0.6.0.dist-info/RECORD
