Metadata-Version: 2.1
Name: lambda-decorators
Version: 0.6.0
Summary: A collection of useful decorators for making AWS Lambda handlers
Home-page: http://lambda-decorators.readthedocs.io
Author: Daniel Schep
Author-email: dschep@gmail.com
License: MIT
Keywords: serverless lambda decorator aws
Platform: UNKNOWN
Classifier: Development Status :: 5 - Production/Stable
Classifier: Environment :: Other Environment
Classifier: Intended Audience :: Developers
Classifier: License :: OSI Approved :: MIT License
Classifier: Programming Language :: Python :: 2
Classifier: Programming Language :: Python :: 2.7
Classifier: Programming Language :: Python :: 3
Classifier: Programming Language :: Python :: 3.6
Requires-Dist: boto3
Provides-Extra: jsonschema
Requires-Dist: jsonschema ; extra == 'jsonschema'
